v6e_utils/__init__.py
v6e_utils/agil_connect/__init__.py
v6e_utils/agil_connect/agil_connect.py
v6e_utils/agil_connect/panel_connect.py
v6e_utils/data_helper/__init__.py
v6e_utils/data_helper/data_helper.py
v6e_utils/data_helper/error.py
v6e_utils/data_helper/record_batch.py
v6e_utils/data_utils.py
v6e_utils/dataframe_helper/__init__.py
v6e_utils/dataframe_helper/df_helper.py
v6e_utils/dataframe_helper/io.py
v6e_utils/dataframe_helper/utils.py
v6e_utils/date_utils.py
v6e_utils/file_utils.py
v6e_utils/model_utils.py
v6e_utils/report_factory/__init__.py
v6e_utils/report_factory/factory.py
v6e_utils/report_factory/loader.py
v6e_utils/report_factory/publisher.py
v6e_utils/report_factory/report_helper.py
v6e_utils/report_factory/reporter.py
v6e_utils/report_factory/runner.py
v6e_utils-0.3.1.dist-info/METADATA
v6e_utils-0.3.1.dist-info/WHEEL
v6e_utils-0.3.1.dist-info/RECORD
