Metadata-Version: 2.1
Name: v6e-utils
Version: 0.3.1
Summary: A collection of utility functions for V6E projects
License: MIT
Author: Luis Valverde
Author-email: lvalverde@istmocenter.com
Requires-Python: >=3.9
Classifier: License :: OSI Approved :: MIT License
Classifier: Programming Language :: Python :: 3
Classifier: Programming Language :: Python :: 3.9
Classifier: Programming Language :: Python :: 3.10
Classifier: Programming Language :: Python :: 3.11
Requires-Dist: django (>=4.0.0)
Requires-Dist: geopy (>=2.2.0)
Requires-Dist: numpy (>=1.20.0)
Requires-Dist: openpyxl (>=3.0.9)
Requires-Dist: pandas (>=1.2.0)
Requires-Dist: pysftp (>=0.2.9)
Requires-Dist: requests (>=2.26.0)
Requires-Dist: tqdm (>=4.62.2)
